{
  "fiche_id": "Aromair_04_4:page_74:015421",
  "source_file": "data\\raw_json\\Aromair_04\\Aromair_04_4.json",
  "page_key": "page_74",
  "source_image": "page_74.jpg",
  "document_type": "client_maintenance_form",
  "company_info": {
    "version": "15.03.22",
    "name": "AROM AIR",
    "slogan": "THE ART OF THE SCENTS",
    "address": {
      "residence": "Résidence OMRANE",
      "street": "Avenue Fattouma Bourguiba",
      "city_postal_code": "La Soukra - 2036 ARIANA"
    }
  },
  "maintenance_details": {
    "client": "Comomile",
    "address": "Soukra",
    "date_raw": "12.04.25",
    "time_raw": "11h20",
    "technician_name": "Bilel",
    "client_maintenance_number": "015421",
    "sav_numbers": [
      "99 289 544",
      "99 289 543"
    ],
    "service_date": "2025-04-12",
    "service_time": "11:20:00"
  },
  "service_type": {
    "demo": null,
    "livraison": true,
    "visite": null,
    "reparation": null,
    "echange": null
  },
  "controle_diffuseur_recharge": [
    {
      "model_diffuseur_raw": "Iceberg RDC",
      "model_diffuseur": "Iceberg",
      "emplacement": "RDC",
      "reference_diffuseur_raw": "CPM",
      "reference_diffuseur": "CPM",
      "nom_parfum": "FDC",
      "reference_bouteille_raw": "S",
      "reference_bouteille": "Simple (S)",
      "qte_parfum_existante_raw": "O",
      "qte_parfum_existante": 0,
      "qualite_diffusion": "P",
      "fuite": "N",
      "en_marche_arret": "A",
      "frequence_diffusion_existante": "5/10",
      "plage_horaire_diffusion": null,
      "motif_arret": "Temps d'arrêt"
    }
  ],
  "recharge_bouteille_effectuee": [
    {
      "ml": 300,
      "parfum": "FDC",
      "reference_bouteille_raw": "S",
      "reference_bouteille": "Simple (S)",
      "frequence_diffusion": "5/10",
      "plage_horaire_fonctionnement": null,
      "emplacement": "RDC"
    }
  ],
  "probleme_recommandation": {
    "probleme_rencontree_raw": "Livraison 300 ml pour diffuseur Iceberg RDC (FC)",
    "probleme_rencontree_code": "LIV",
    "solution_proposee": "changement selencieux"
  },
  "enquete_satisfaction_client": {
    "satisfied_service": true,
    "parfum_bien_diffuse": true
  },
  "signature_cachet": {
    "text": "CAMOMILLE CONCEF\nTel: 22 133 505"
  },
  "raw_payload": {
    "source_image": "page_74.jpg",
    "document_type": "client_maintenance_form",
    "company_info": {
      "version": "15.03.22",
      "name": "AROM AIR",
      "slogan": "THE ART OF THE SCENTS",
      "address": {
        "residence": "Résidence OMRANE",
        "street": "Avenue Fattouma Bourguiba",
        "city_postal_code": "La Soukra - 2036 ARIANA"
      }
    },
    "maintenance_details": {
      "client": "Comomile",
      "address": "Soukra",
      "date_raw": "12.04.25",
      "time_raw": "11h20",
      "technician_name": "Bilel",
      "client_maintenance_number": "015421",
      "sav_numbers": [
        "99 289 544",
        "99 289 543"
      ]
    },
    "service_type": {
      "demo": null,
      "livraison": true,
      "visite": null,
      "reparation": null,
      "echange": null
    },
    "controle_diffuseur_recharge": [
      {
        "model_diffuseur_raw": "Iceberg RDC",
        "model_diffuseur": "Iceberg",
        "emplacement": "RDC",
        "reference_diffuseur_raw": "CPM",
        "reference_diffuseur": "CPM",
        "nom_parfum": "FDC",
        "reference_bouteille_raw": "S",
        "reference_bouteille": "Simple (S)",
        "qte_parfum_existante_raw": "O",
        "qte_parfum_existante": 0,
        "qualite_diffusion": "P",
        "fuite": "N",
        "en_marche_arret": "A",
        "frequence_diffusion_existante": "5/10",
        "plage_horaire_diffusion": null,
        "motif_arret": "Temps d'arrêt"
      }
    ],
    "recharge_bouteille_effectuee": [
      {
        "ml": 300,
        "parfum": "FDC",
        "reference_bouteille_raw": "S",
        "reference_bouteille": "Simple (S)",
        "frequence_diffusion": "5/10",
        "plage_horaire_fonctionnement": null,
        "emplacement": "RDC"
      }
    ],
    "probleme_recommandation": {
      "probleme_rencontree_raw": "Livraison 300 ml pour diffuseur Iceberg RDC (FC)",
      "probleme_rencontree_code": "LIV",
      "solution_proposee": "changement selencieux"
    },
    "enquete_satisfaction_client": {
      "satisfied_service": true,
      "parfum_bien_diffuse": true
    },
    "signature_cachet": {
      "text": "CAMOMILLE CONCEF\nTel: 22 133 505"
    }
  }
}
