{
  "fiche_id": "Aromair_01_02:page_28:014965",
  "source_file": "data\\raw_json\\Aromair_02\\Aromair_01_02.json",
  "page_key": "page_28",
  "source_image": null,
  "document_type": "client_maintenance_form",
  "company_info": {
    "version": "15.03.22",
    "name": "AROMAIR",
    "slogan": "THE ART OF THE SCENTS",
    "address": {
      "residence": "Résidence OMRANE",
      "street": "Avenue Fattouma Bourguiba",
      "city_postal_code": "La Soukra - 2036 ARIANA"
    }
  },
  "maintenance_details": {
    "client": "AP Collection",
    "address": "Menzah4",
    "date_raw": "07.02.25",
    "time_raw": "13H15",
    "technician_name": null,
    "client_maintenance_number": "014965",
    "sav_numbers": [
      "99 289 544",
      "99 289 543"
    ],
    "service_date": "2025-02-07",
    "service_time": "13:15:00"
  },
  "service_type": {
    "demo": null,
    "livraison": true,
    "visite": true,
    "reparation": null,
    "echange": null
  },
  "controle_diffuseur_recharge": [
    {
      "model_diffuseur_raw": "ASTREE RDC",
      "model_diffuseur": "Astree",
      "emplacement": "RDC",
      "reference_diffuseur_raw": "CPM",
      "reference_diffuseur": "CPM",
      "nom_parfum": null,
      "reference_bouteille_raw": "S",
      "reference_bouteille": "Simple (S)",
      "qte_parfum_existante_raw": "288",
      "qte_parfum_existante": 288,
      "qualite_diffusion": "B",
      "fuite": "N",
      "en_marche_arret": "M",
      "frequence_diffusion_existante": "5-10",
      "plage_horaire_diffusion": null,
      "motif_arret": null
    },
    {
      "model_diffuseur_raw": "ICEBERG 1er",
      "model_diffuseur": "Iceberg",
      "emplacement": "1er",
      "reference_diffuseur_raw": "CPM",
      "reference_diffuseur": "CPM",
      "nom_parfum": null,
      "reference_bouteille_raw": "S",
      "reference_bouteille": "Simple (S)",
      "qte_parfum_existante_raw": "O",
      "qte_parfum_existante": 0,
      "qualite_diffusion": "B",
      "fuite": "N",
      "en_marche_arret": "M",
      "frequence_diffusion_existante": "5-10",
      "plage_horaire_diffusion": null,
      "motif_arret": null
    },
    {
      "model_diffuseur_raw": "AR100 WC",
      "model_diffuseur": "Aromair100",
      "emplacement": "WC",
      "reference_diffuseur_raw": null,
      "reference_diffuseur": null,
      "nom_parfum": null,
      "reference_bouteille_raw": "S",
      "reference_bouteille": "Simple (S)",
      "qte_parfum_existante_raw": null,
      "qte_parfum_existante": null,
      "qualite_diffusion": null,
      "fuite": null,
      "en_marche_arret": null,
      "frequence_diffusion_existante": null,
      "plage_horaire_diffusion": null,
      "motif_arret": null
    }
  ],
  "recharge_bouteille_effectuee": [
    {
      "ml": 300,
      "parfum": null,
      "reference_bouteille_raw": "S",
      "reference_bouteille": "Simple (S)",
      "frequence_diffusion": "5-10",
      "plage_horaire_fonctionnement": "RDC",
      "emplacement": "WC-1"
    },
    {
      "ml": 300,
      "parfum": null,
      "reference_bouteille_raw": "S",
      "reference_bouteille": "Simple (S)",
      "frequence_diffusion": "5-10",
      "plage_horaire_fonctionnement": "V",
      "emplacement": "RDC"
    },
    {
      "ml": 300,
      "parfum": null,
      "reference_bouteille_raw": null,
      "reference_bouteille": null,
      "frequence_diffusion": null,
      "plage_horaire_fonctionnement": null,
      "emplacement": null
    }
  ],
  "probleme_recommandation": {
    "probleme_rencontree_raw": "Livraison 300ml FC2 au RDC et au 1er étage + LIV recharge WC et RDC",
    "probleme_rencontree_code": "LIV",
    "solution_proposee": null
  },
  "enquete_satisfaction_client": {
    "satisfied_service": null,
    "parfum_bien_diffuse": null
  },
  "signature_cachet": {
    "text": null
  },
  "raw_payload": {
    "document_type": "client_maintenance_form",
    "company_info": {
      "version": "15.03.22",
      "name": "AROMAIR",
      "slogan": "THE ART OF THE SCENTS",
      "address": {
        "residence": "Résidence OMRANE",
        "street": "Avenue Fattouma Bourguiba",
        "city_postal_code": "La Soukra - 2036 ARIANA"
      }
    },
    "maintenance_details": {
      "client": "AP Collection",
      "address": "Menzah4",
      "date_raw": "07.02.25",
      "time_raw": "13H15",
      "technician_name": null,
      "client_maintenance_number": "014965",
      "sav_numbers": [
        "99 289 544",
        "99 289 543"
      ]
    },
    "service_type": {
      "demo": null,
      "livraison": true,
      "visite": true,
      "reparation": null,
      "echange": null
    },
    "controle_diffuseur_recharge": [
      {
        "model_diffuseur_raw": "ASTREE RDC",
        "model_diffuseur": "Astree",
        "emplacement": "RDC",
        "reference_diffuseur_raw": "CPM",
        "reference_diffuseur": "CPM",
        "nom_parfum": null,
        "reference_bouteille_raw": "S",
        "reference_bouteille": "Simple (S)",
        "qte_parfum_existante_raw": "288",
        "qte_parfum_existante": 288,
        "qualite_diffusion": "B",
        "fuite": "N",
        "en_marche_arret": "M",
        "frequence_diffusion_existante": "5-10",
        "plage_horaire_diffusion": null,
        "motif_arret": null
      },
      {
        "model_diffuseur_raw": "ICEBERG 1er",
        "model_diffuseur": "Iceberg",
        "emplacement": "1er",
        "reference_diffuseur_raw": "CPM",
        "reference_diffuseur": "CPM",
        "nom_parfum": null,
        "reference_bouteille_raw": "S",
        "reference_bouteille": "Simple (S)",
        "qte_parfum_existante_raw": "O",
        "qte_parfum_existante": 0,
        "qualite_diffusion": "B",
        "fuite": "N",
        "en_marche_arret": "M",
        "frequence_diffusion_existante": "5-10",
        "plage_horaire_diffusion": null,
        "motif_arret": null
      },
      {
        "model_diffuseur_raw": "AR100 WC",
        "model_diffuseur": "Aromair100",
        "emplacement": "WC",
        "reference_diffuseur_raw": null,
        "reference_diffuseur": null,
        "nom_parfum": null,
        "reference_bouteille_raw": "S",
        "reference_bouteille": "Simple (S)",
        "qte_parfum_existante_raw": null,
        "qte_parfum_existante": null,
        "qualite_diffusion": null,
        "fuite": null,
        "en_marche_arret": null,
        "frequence_diffusion_existante": null,
        "plage_horaire_diffusion": null,
        "motif_arret": null
      }
    ],
    "recharge_bouteille_effectuee": [
      {
        "ml": 300,
        "parfum": null,
        "reference_bouteille_raw": "S",
        "reference_bouteille": "Simple (S)",
        "frequence_diffusion": "5-10",
        "plage_horaire_fonctionnement": "RDC",
        "emplacement": "WC-1"
      },
      {
        "ml": 300,
        "parfum": null,
        "reference_bouteille_raw": "S",
        "reference_bouteille": "Simple (S)",
        "frequence_diffusion": "5-10",
        "plage_horaire_fonctionnement": "V",
        "emplacement": "RDC"
      },
      {
        "ml": 300,
        "parfum": null,
        "reference_bouteille_raw": null,
        "reference_bouteille": null,
        "frequence_diffusion": null,
        "plage_horaire_fonctionnement": null,
        "emplacement": null
      }
    ],
    "probleme_recommandation": {
      "probleme_rencontree_raw": "Livraison 300ml FC2 au RDC et au 1er étage + LIV recharge WC et RDC",
      "probleme_rencontree_code": "LIV",
      "solution_proposee": null
    },
    "enquete_satisfaction_client": {
      "satisfied_service": null,
      "parfum_bien_diffuse": null
    },
    "signature_cachet": {
      "text": null
    }
  }
}
